pydantic_ai_examples/__main__.py
pydantic_ai_examples/bank_support.py
pydantic_ai_examples/chat_app.html
pydantic_ai_examples/chat_app.py
pydantic_ai_examples/chat_app.ts
pydantic_ai_examples/data_analyst.py
pydantic_ai_examples/flight_booking.py
pydantic_ai_examples/py.typed
pydantic_ai_examples/pydantic_model.py
pydantic_ai_examples/question_graph.py
pydantic_ai_examples/rag.py
pydantic_ai_examples/roulette_wheel.py
pydantic_ai_examples/sql_gen.py
pydantic_ai_examples/stream_markdown.py
pydantic_ai_examples/stream_whales.py
pydantic_ai_examples/weather_agent.py
pydantic_ai_examples/weather_agent_gradio.py
pydantic_ai_examples/ag_ui/__init__.py
pydantic_ai_examples/ag_ui/__main__.py
pydantic_ai_examples/ag_ui/api/__init__.py
pydantic_ai_examples/ag_ui/api/agentic_chat.py
pydantic_ai_examples/ag_ui/api/agentic_generative_ui.py
pydantic_ai_examples/ag_ui/api/human_in_the_loop.py
pydantic_ai_examples/ag_ui/api/predictive_state_updates.py
pydantic_ai_examples/ag_ui/api/shared_state.py
pydantic_ai_examples/ag_ui/api/tool_based_generative_ui.py
pydantic_ai_examples/evals/__init__.py
pydantic_ai_examples/evals/agent.py
pydantic_ai_examples/evals/custom_evaluators.py
pydantic_ai_examples/evals/example_01_generate_dataset.py
pydantic_ai_examples/evals/example_02_add_custom_evaluators.py
pydantic_ai_examples/evals/example_03_unit_testing.py
pydantic_ai_examples/evals/example_04_compare_models.py
pydantic_ai_examples/evals/models.py
pydantic_ai_examples/evals/datasets/time_range_v1.yaml
pydantic_ai_examples/evals/datasets/time_range_v1_schema.json
pydantic_ai_examples/evals/datasets/time_range_v2.yaml
pydantic_ai_examples/evals/datasets/time_range_v2_schema.json
pydantic_ai_examples/slack_lead_qualifier/__init__.py
pydantic_ai_examples/slack_lead_qualifier/agent.py
pydantic_ai_examples/slack_lead_qualifier/app.py
pydantic_ai_examples/slack_lead_qualifier/functions.py
pydantic_ai_examples/slack_lead_qualifier/modal.py
pydantic_ai_examples/slack_lead_qualifier/models.py
pydantic_ai_examples-1.51.0.dist-info/METADATA
pydantic_ai_examples-1.51.0.dist-info/WHEEL
pydantic_ai_examples-1.51.0.dist-info/licenses/LICENSE
pydantic_ai_examples-1.51.0.dist-info/RECORD
