Metadata-Version: 2.4
Name: pydantic-ai-examples
Version: 1.51.0
Summary: Examples of how to use Pydantic AI and what it can do.
Author-email: Samuel Colvin <samuel@pydantic.dev>, Marcelo Trylesinski <marcelotryle@gmail.com>, David Montague <david@pydantic.dev>, Alex Hall <alex@pydantic.dev>, Douwe Maan <douwe@pydantic.dev>
License-Expression: MIT
License-File: LICENSE
Classifier: Development Status :: 5 - Production/Stable
Classifier: Environment :: Console
Classifier: Environment :: MacOS X
Classifier: Intended Audience :: Developers
Classifier: Intended Audience :: Information Technology
Classifier: Intended Audience :: System Administrators
Classifier: License :: OSI Approved :: MIT License
Classifier: Operating System :: POSIX :: Linux
Classifier: Operating System :: Unix
Classifier: Programming Language :: Python
Classifier: Programming Language :: Python :: 3
Classifier: Programming Language :: Python :: 3 :: Only
Classifier: Programming Language :: Python :: 3.10
Classifier: Programming Language :: Python :: 3.11
Classifier: Programming Language :: Python :: 3.12
Classifier: Programming Language :: Python :: 3.13
Classifier: Topic :: Internet
Classifier: Topic :: Software Development :: Libraries :: Python Modules
Requires-Python: >=3.10
Requires-Dist: asyncpg>=0.30.0
Requires-Dist: datasets>=4.0.0
Requires-Dist: devtools>=0.12.2
Requires-Dist: duckdb>=1.3.2
Requires-Dist: fastapi>=0.115.4
Requires-Dist: gradio>=5.31.0
Requires-Dist: logfire[asyncpg,fastapi,httpx,sqlite3]>=3.14.1
Requires-Dist: mcp[cli]<2.0,>=1.25.0
Requires-Dist: modal>=1.0.4
Requires-Dist: pandas>=2.2.3
Requires-Dist: pydantic-ai-slim[ag-ui,anthropic,groq,openai,vertexai]==1.51.0
Requires-Dist: pydantic-evals==1.51.0
Requires-Dist: python-multipart>=0.0.17
Requires-Dist: rich>=13.9.2
Requires-Dist: uvicorn>=0.32.0
